{
  "version": "1.0.2",
  "description": "Composooor",
  "proposedName": "Composooor Snap",
  "repository": {
    "type": "git",
    "url": "git+https://github.com/kairos-loan/composooor.git"
  },
  "source": {
    "shasum": "UNlp7+PwU0Q4chWUmP9QcgfOFWMxu/nEzf6EcvPioJY=",
    "location": {
      "npm": {
        "filePath": "dist/bundle.js",
        "iconPath": "images/icon.svg",
        "packageName": "@composooor/snap",
        "registry": "https://registry.npmjs.org/"
      }
    }
  },
  "initialPermissions": {
    "snap_dialog": {},
    "endowment:rpc": {
      "dapps": true,
      "snaps": false
    },
    "endowment:network-access": {},
    "endowment:ethereum-provider": {},
    "snap_getEntropy": {}
  },
  "manifestVersion": "0.1"
}
